README.txt
setup.py
genshi_view/__init__.py
genshi_view.egg-info/PKG-INFO
genshi_view.egg-info/SOURCES.txt
genshi_view.egg-info/dependency_links.txt
genshi_view.egg-info/entry_points.txt
genshi_view.egg-info/not-zip-safe
genshi_view.egg-info/requires.txt
genshi_view.egg-info/top_level.txt