Metadata-Version: 1.0
Name: genshi-view
Version: 0.3.2
Summary: paste template for a view using webob + genshi
Home-page: http://k0s.org/hg/genshi_view
Author: Jeff Hammel
Author-email: k0scist@gmail.com
License: GPL
Platform: UNKNOWN
